{
    "areas": [
        {
            "name": "hoenn-altering-cave-a",
            "url": "/api/v2/location-area/441/"
        },
        {
            "name": "hoenn-altering-cave-b",
            "url": "/api/v2/location-area/442/"
        },
        {
            "name": "hoenn-altering-cave-c",
            "url": "/api/v2/location-area/443/"
        },
        {
            "name": "hoenn-altering-cave-d",
            "url": "/api/v2/location-area/444/"
        },
        {
            "name": "hoenn-altering-cave-e",
            "url": "/api/v2/location-area/445/"
        },
        {
            "name": "hoenn-altering-cave-f",
            "url": "/api/v2/location-area/446/"
        },
        {
            "name": "hoenn-altering-cave-g",
            "url": "/api/v2/location-area/447/"
        },
        {
            "name": "hoenn-altering-cave-h",
            "url": "/api/v2/location-area/448/"
        },
        {
            "name": "hoenn-altering-cave-i",
            "url": "/api/v2/location-area/449/"
        }
    ],
    "game_indices": [],
    "id": 490,
    "name": "hoenn-altering-cave",
    "names": [
        {
            "language": {
                "name": "en",
                "url": "/api/v2/language/9/"
            },
            "name": "Altering Cave"
        },
        {
            "language": {
                "name": "fr",
                "url": "/api/v2/language/5/"
            },
            "name": "Grotte M\u00e9tamo"
        }
    ],
    "region": {
        "name": "hoenn",
        "url": "/api/v2/region/3/"
    }
}