{
    "areas": [],
    "game_indices": [
        {
            "game_index": 336,
            "generation": {
                "name": "generation-vi",
                "url": "/api/v2/generation/6/"
            }
        }
    ],
    "id": 701,
    "name": "pathless-plain",
    "names": [
        {
            "language": {
                "name": "ja",
                "url": "/api/v2/language/11/"
            },
            "name": "\u540d\u3082\u306a\u304d\u5e73\u539f"
        },
        {
            "language": {
                "name": "en",
                "url": "/api/v2/language/9/"
            },
            "name": "Pathless Plain"
        },
        {
            "language": {
                "name": "it",
                "url": "/api/v2/language/8/"
            },
            "name": "Piana Senza Nome"
        },
        {
            "language": {
                "name": "es",
                "url": "/api/v2/language/7/"
            },
            "name": "Llanura Sinnombre"
        },
        {
            "language": {
                "name": "de",
                "url": "/api/v2/language/6/"
            },
            "name": "Namenlose Ebene"
        },
        {
            "language": {
                "name": "fr",
                "url": "/api/v2/language/5/"
            },
            "name": "Plaine Sans Nom"
        },
        {
            "language": {
                "name": "ko",
                "url": "/api/v2/language/3/"
            },
            "name": "\uc774\ub984\uc5c6\ub294 \ud3c9\uc6d0"
        },
        {
            "language": {
                "name": "ja-Hrkt",
                "url": "/api/v2/language/1/"
            },
            "name": "\u306a\u3082\u306a\u304d\u3078\u3044\u3052\u3093"
        }
    ],
    "region": {
        "name": "hoenn",
        "url": "/api/v2/region/3/"
    }
}